fastica_torch/__init__.py
fastica_torch/fastica.py
fastica_torch-0.1.1.dist-info/licenses/LICENSE
fastica_torch-0.1.1.dist-info/METADATA
fastica_torch-0.1.1.dist-info/WHEEL
fastica_torch-0.1.1.dist-info/top_level.txt
fastica_torch-0.1.1.dist-info/RECORD
