Metadata-Version: 2.4
Name: fastica_torch
Version: 0.1.1
Summary: PyTorch implementation of the FastICA algorithm for Independent Component Analysis
Author: Richard Hakim
License: MIT
Project-URL: Homepage, https://github.com/RichieHakim/FastICA_torch
Project-URL: Bug Tracker, https://github.com/RichieHakim/FastICA_torch/issues
Keywords: ica,independent-component-analysis,fastica,pytorch,machine-learning,signal-processing
Classifier: Development Status :: 4 - Beta
Classifier: Intended Audience :: Science/Research
Classifier: License :: OSI Approved :: MIT License
Classifier: Programming Language :: Python :: 3
Classifier: Programming Language :: Python :: 3.9
Classifier: Programming Language :: Python :: 3.10
Classifier: Programming Language :: Python :: 3.11
Classifier: Programming Language :: Python :: 3.12
Classifier: Topic :: Scientific/Engineering
Classifier: Topic :: Scientific/Engineering :: Artificial Intelligence
Requires-Python: >=3.9
License-File: LICENSE
Requires-Dist: torch>=2.0
Requires-Dist: numpy>=1.20
Provides-Extra: dev
Requires-Dist: pytest>=7.0; extra == "dev"
Requires-Dist: scikit-learn>=1.0; extra == "dev"
Dynamic: license-file
